aiohttp_apispec/__init__.py
aiohttp_apispec/aiohttp_apispec.py
aiohttp_apispec/middlewares.py
aiohttp_apispec/utils.py
aiohttp_apispec/decorators/__init__.py
aiohttp_apispec/decorators/docs.py
aiohttp_apispec/decorators/request.py
aiohttp_apispec/decorators/response.py
aiohttp_apispec/static/favicon-16x16.png
aiohttp_apispec/static/favicon-32x32.png
aiohttp_apispec/static/index.html
aiohttp_apispec/static/oauth2-redirect.html
aiohttp_apispec/static/swagger-ui-bundle.js
aiohttp_apispec/static/swagger-ui-bundle.js.map
aiohttp_apispec/static/swagger-ui-standalone-preset.js
aiohttp_apispec/static/swagger-ui-standalone-preset.js.map
aiohttp_apispec/static/swagger-ui.css
aiohttp_apispec/static/swagger-ui.css.map
aiohttp_apispec/static/swagger-ui.js
aiohttp_apispec/static/swagger-ui.js.map
aiohttp_apispec_acapy-3.0.3.dist-info/LICENSE
aiohttp_apispec_acapy-3.0.3.dist-info/METADATA
aiohttp_apispec_acapy-3.0.3.dist-info/WHEEL
aiohttp_apispec_acapy-3.0.3.dist-info/top_level.txt
aiohttp_apispec_acapy-3.0.3.dist-info/RECORD
