Metadata-Version: 2.2
Name: aiohttp-apispec-acapy
Version: 3.0.3
Summary: Build and document REST APIs with aiohttp and apispec
Home-page: https://github.com/jamshale/aiohttp-apispec
Author: Jamie Hale
Author-email: jamiehalebc@gmail.com
License: MIT
Keywords: aiohttp marshmallow apispec swagger
Classifier: Development Status :: 5 - Production/Stable
Classifier: Intended Audience :: Developers
Classifier: License :: OSI Approved :: MIT License
Classifier: Natural Language :: English
Classifier: Programming Language :: Python :: 3.9
Classifier: Programming Language :: Python :: 3.10
Classifier: Programming Language :: Python :: 3.11
Classifier: Programming Language :: Python :: 3.12
Requires-Python: >=3.9
License-File: LICENSE
Requires-Dist: aiohttp<4.0,>=3.9.4
Requires-Dist: apispec>=6.6.1
Requires-Dist: webargs>=8.4.0
Requires-Dist: jinja2>=3.1.3
Dynamic: author
Dynamic: author-email
Dynamic: classifier
Dynamic: description
Dynamic: description-content-type
Dynamic: home-page
Dynamic: keywords
Dynamic: license
Dynamic: requires-dist
Dynamic: requires-python
Dynamic: summary
